{
    "rulesDirectory": [
        "../../codelyzer",
        "../../rxjs-tslint"
    ],
    "extends": [
        "rxjs-tslint-rules"
    ],
    "rules": {
        // doc/lint/formatting.md
        "encoding": true,
        "file-header": false,
        "file-name-casing": [true, "kebab-case"],
        "import-spacing": true,
        "no-consecutive-blank-lines": [true, 3],
        "no-irregular-whitespace": true,
        "no-trailing-whitespace": true,
        "one-line": [true, "check-catch", "check-finally", "check-else", "check-open-brace", "check-whitespace"],
        "quotemark": [true, "single", "avoid-escape", "avoid-template"],
        "semicolon": [true, "always"],
        "space-before-function-paren": [true, {"anonymous": "always", "named": "never", "asyncArrow": "always", "constructor": "never", "method": "never"}],
        "space-within-parens": [true, 0],
        "whitespace": [true, "check-branch", "check-decl", "check-operator", "check-module", "check-separator", "check-rest-spread", "check-type", "check-type-operator", "check-preblock"],
        "eofline": true,
        "indent": [true, "spaces", 4],
        "linebreak-style": false,
        "max-file-line-count": [true, 1600],
        "max-line-length": [true, 140],
        "curly": true,
        "no-invalid-template-strings": true,
        "typedef-whitespace": [true, {"call-signature": "nospace", "index-signature": "nospace", "parameter": "nospace", "property-declaration": "nospace", "variable-declaration": "nospace"}, {"call-signature": "onespace", "index-signature": "onespace", "parameter": "onespace", "property-declaration": "onespace", "variable-declaration": "onespace"}],
        "angular-whitespace": [true, "check-interpolation", "check-semicolon"],
        "import-destructuring-spacing": true,

        // doc/lint/comments.md
        "comment-format": [true, "check-space"],
        "completed-docs": false,
        "jsdoc-format": false,
        "no-redundant-jsdoc": false
    }
}
